biplex_utils_hash/__init__.py
biplex_utils_hash/hashing.py
biplex_utils_hash/json.py
biplex_utils_hash/normalizer.py
biplex_utils_hash/py.typed
biplex_utils_hash/uuid.py
biplex_utils_hash-0.1.0.dist-info/licenses/LICENSE
biplex_utils_hash-0.1.0.dist-info/METADATA
biplex_utils_hash-0.1.0.dist-info/WHEEL
biplex_utils_hash-0.1.0.dist-info/top_level.txt
biplex_utils_hash-0.1.0.dist-info/RECORD
